IbmDeveloperworksQuanbuWenzhangDierBufenFix1/README.md
IbmDeveloperworksQuanbuWenzhangDierBufenFix1/__init__.py
IbmDeveloperworksQuanbuWenzhangDierBufenFix1/__main__.py
IbmDeveloperworksQuanbuWenzhangDierBufenFix1/file.epub
IbmDeveloperworksQuanbuWenzhangDierBufenFix1/index.html
IbmDeveloperworksQuanbuWenzhangDierBufenFix1/css/__init__.py
IbmDeveloperworksQuanbuWenzhangDierBufenFix1/css/annotations.css
IbmDeveloperworksQuanbuWenzhangDierBufenFix1/css/main.css
IbmDeveloperworksQuanbuWenzhangDierBufenFix1/css/normalize.css
IbmDeveloperworksQuanbuWenzhangDierBufenFix1/css/popup.css
IbmDeveloperworksQuanbuWenzhangDierBufenFix1/font/__init__.py
IbmDeveloperworksQuanbuWenzhangDierBufenFix1/font/fontello.eot
IbmDeveloperworksQuanbuWenzhangDierBufenFix1/font/fontello.svg
IbmDeveloperworksQuanbuWenzhangDierBufenFix1/font/fontello.ttf
IbmDeveloperworksQuanbuWenzhangDierBufenFix1/font/fontello.woff
IbmDeveloperworksQuanbuWenzhangDierBufenFix1/img/__init__.py
IbmDeveloperworksQuanbuWenzhangDierBufenFix1/img/annotator-glyph-sprite.png
IbmDeveloperworksQuanbuWenzhangDierBufenFix1/img/annotator-icon-sprite.png
IbmDeveloperworksQuanbuWenzhangDierBufenFix1/img/apple-touch-icon.png
IbmDeveloperworksQuanbuWenzhangDierBufenFix1/img/cancelfullscreen.png
IbmDeveloperworksQuanbuWenzhangDierBufenFix1/img/close.png
IbmDeveloperworksQuanbuWenzhangDierBufenFix1/img/fullscreen.png
IbmDeveloperworksQuanbuWenzhangDierBufenFix1/img/loader.gif
IbmDeveloperworksQuanbuWenzhangDierBufenFix1/img/menu-icon.png
IbmDeveloperworksQuanbuWenzhangDierBufenFix1/img/save.png
IbmDeveloperworksQuanbuWenzhangDierBufenFix1/img/saved.png
IbmDeveloperworksQuanbuWenzhangDierBufenFix1/img/settings-s.png
IbmDeveloperworksQuanbuWenzhangDierBufenFix1/img/settings.png
IbmDeveloperworksQuanbuWenzhangDierBufenFix1/img/star.png
IbmDeveloperworksQuanbuWenzhangDierBufenFix1/js/__init__.py
IbmDeveloperworksQuanbuWenzhangDierBufenFix1/js/epub.js
IbmDeveloperworksQuanbuWenzhangDierBufenFix1/js/epub.min.js
ibm_developerworks_quanbu_wenzhang_dier_bufen_fix1-2025.3.25.1.dist-info/METADATA
ibm_developerworks_quanbu_wenzhang_dier_bufen_fix1-2025.3.25.1.dist-info/WHEEL
ibm_developerworks_quanbu_wenzhang_dier_bufen_fix1-2025.3.25.1.dist-info/entry_points.txt
ibm_developerworks_quanbu_wenzhang_dier_bufen_fix1-2025.3.25.1.dist-info/top_level.txt
ibm_developerworks_quanbu_wenzhang_dier_bufen_fix1-2025.3.25.1.dist-info/RECORD
